scheme/__init__.py
scheme/common.py
scheme/element.py
scheme/exceptions.py
scheme/field.py
scheme/format.py
scheme/interpolation.py
scheme/surrogate.py
scheme/timezone.py
scheme/util.py
scheme/doc/__init__.py
scheme/doc/domain.py
scheme/doc/generator.py
scheme/fields/__init__.py
scheme/fields/binary.py
scheme/fields/boolean.py
scheme/fields/date.py
scheme/fields/datetime.py
scheme/fields/decimal.py
scheme/fields/definition.py
scheme/fields/email.py
scheme/fields/enumeration.py
scheme/fields/error.py
scheme/fields/float.py
scheme/fields/integer.py
scheme/fields/map.py
scheme/fields/object.py
scheme/fields/sequence.py
scheme/fields/structure.py
scheme/fields/surrogate.py
scheme/fields/text.py
scheme/fields/time.py
scheme/fields/token.py
scheme/fields/tuple.py
scheme/fields/union.py
scheme/fields/uuid.py
scheme/formats/__init__.py
scheme/formats/csv.py
scheme/formats/json.py
scheme/formats/structuredtext.py
scheme/formats/urlencoded.py
scheme/formats/xml.py
scheme/formats/yaml.py
pyscheme-2.0.3.dist-info/LICENSE
pyscheme-2.0.3.dist-info/METADATA
pyscheme-2.0.3.dist-info/WHEEL
pyscheme-2.0.3.dist-info/top_level.txt
pyscheme-2.0.3.dist-info/RECORD
