Metadata-Version: 2.1
Name: pyscheme
Version: 2.0.3
Summary: A declarative schema framework.
Home-page: https://github.com/arterial-io/scheme
Author: Jordan McCoy
Author-email: mccoy.jordan@gmail.com
License: BSD
Keywords: schema data validation structured api
Platform: UNKNOWN
Classifier: Development Status :: 5 - Production/Stable
Classifier: Intended Audience :: Developers
Classifier: Natural Language :: English
Classifier: License :: OSI Approved :: BSD License
Classifier: Programming Language :: Python
Classifier: Programming Language :: Python :: 2.6
Classifier: Programming Language :: Python :: 2.7
Classifier: Programming Language :: Python :: 3.3
Classifier: Programming Language :: Python :: 3.4
Classifier: Topic :: Software Development :: Libraries
Classifier: Topic :: Software Development :: Libraries :: Python Modules
Requires-Dist: Jinja2 (>=2.7)
Requires-Dist: PyYAML (>=3)
